plover_stenograph_usb.py
plover_stenograph_usb-1.3.0.dist-info/LICENSE.txt
plover_stenograph_usb-1.3.0.dist-info/METADATA
plover_stenograph_usb-1.3.0.dist-info/WHEEL
plover_stenograph_usb-1.3.0.dist-info/entry_points.txt
plover_stenograph_usb-1.3.0.dist-info/top_level.txt
plover_stenograph_usb-1.3.0.dist-info/zip-safe
plover_stenograph_usb-1.3.0.dist-info/RECORD
