Metadata-Version: 2.1
Name: plover-stenograph-usb
Version: 1.3.0
Summary: Stenograph USB protocol for Diamanté and Luminex machines for Plover
Home-page: https://github.com/morinted/plover_stenograph_usb
Author: Ted Morin
Author-email: morinted@gmail.com
License: GNU General Public License v2 or later (GPLv2+)
Keywords: plover plover_plugin
Platform: UNKNOWN
Classifier: Development Status :: 4 - Beta
Classifier: Environment :: Plugins
Classifier: Intended Audience :: End Users/Desktop
Classifier: License :: OSI Approved :: GNU General Public License v2 or later (GPLv2+)
Classifier: Operating System :: OS Independent
Classifier: Programming Language :: Python :: 3
Classifier: Programming Language :: Python :: 3.4
Classifier: Programming Language :: Python :: 3.5
Classifier: Programming Language :: Python :: 3.6
License-File: LICENSE.txt
Requires-Dist: plover (>=4.0.0.dev5)
Requires-Dist: more-itertools (>=6.0.0)
Requires-Dist: pyusb (>=1.0.0) ; platform_system != "Windows"
Requires-Dist: pyusb-libusb1-backend ; platform_system != "Windows"
